thousandeyes_sdk/streaming/__init__.py
thousandeyes_sdk/streaming/py.typed
thousandeyes_sdk/streaming/api/__init__.py
thousandeyes_sdk/streaming/api/streaming_api.py
thousandeyes_sdk/streaming/models/__init__.py
thousandeyes_sdk/streaming/models/api_error.py
thousandeyes_sdk/streaming/models/api_error_integration_limits.py
thousandeyes_sdk/streaming/models/audit_operation.py
thousandeyes_sdk/streaming/models/audit_operation_with_update.py
thousandeyes_sdk/streaming/models/bad_request_error.py
thousandeyes_sdk/streaming/models/create_stream_response.py
thousandeyes_sdk/streaming/models/data_model_version.py
thousandeyes_sdk/streaming/models/endpoint_agent_label.py
thousandeyes_sdk/streaming/models/endpoint_type.py
thousandeyes_sdk/streaming/models/exporter_config.py
thousandeyes_sdk/streaming/models/exporter_config_authorization.py
thousandeyes_sdk/streaming/models/exporter_config_o_auth2.py
thousandeyes_sdk/streaming/models/exporter_config_splunk_hec.py
thousandeyes_sdk/streaming/models/filters.py
thousandeyes_sdk/streaming/models/filters_test_types.py
thousandeyes_sdk/streaming/models/get_stream_response.py
thousandeyes_sdk/streaming/models/put_stream.py
thousandeyes_sdk/streaming/models/signal.py
thousandeyes_sdk/streaming/models/stream.py
thousandeyes_sdk/streaming/models/stream_links.py
thousandeyes_sdk/streaming/models/stream_response.py
thousandeyes_sdk/streaming/models/stream_self_link.py
thousandeyes_sdk/streaming/models/stream_status.py
thousandeyes_sdk/streaming/models/stream_status_type.py
thousandeyes_sdk/streaming/models/stream_type.py
thousandeyes_sdk/streaming/models/tag_match.py
thousandeyes_sdk/streaming/models/tag_match_object_type.py
thousandeyes_sdk/streaming/models/test_match.py
thousandeyes_sdk/streaming/models/test_match_domain.py
thousandeyes_sdk/streaming/models/test_type.py
thousandeyes_sdk/streaming/models/unauthorized_error.py
thousandeyes_sdk_streaming-2.23.0.dist-info/licenses/LICENSE
thousandeyes_sdk_streaming-2.23.0.dist-info/licenses/NOTICE
thousandeyes_sdk_streaming-2.23.0.dist-info/METADATA
thousandeyes_sdk_streaming-2.23.0.dist-info/WHEEL
thousandeyes_sdk_streaming-2.23.0.dist-info/top_level.txt
thousandeyes_sdk_streaming-2.23.0.dist-info/RECORD
